{"appleSKU":"","products":[{"id":"gold9","type":0,"storeIDs":[],"defaultDescription":{"googleLocale":4,"title":"Gives you 9 Gold coins","description":"Gives you 9 Gold coins"},"screenshotPath":"","applePriceTier":1,"googlePrice":{"data":[35,0,0,0],"num":35.0},"pricingTemplateID":"","descriptions":[]},{"id":"gold15","type":0,"storeIDs":[],"defaultDescription":{"googleLocale":4,"title":"Gives you 15 Gold coins","description":"Gives you 15 Gold coins"},"screenshotPath":"","applePriceTier":2,"googlePrice":{"data":[85,0,0,0],"num":85.0},"pricingTemplateID":"","descriptions":[]},{"id":"gold25","type":0,"storeIDs":[],"defaultDescription":{"googleLocale":4,"title":"Gives you 25 Gold coins","description":"Gives you 25 Gold coins"},"screenshotPath":"","applePriceTier":3,"googlePrice":{"data":[100,0,0,0],"num":100.0},"pricingTemplateID":"","descriptions":[]},{"id":"gold50","type":0,"storeIDs":[],"defaultDescription":{"googleLocale":4,"title":"Gives you 50 Gold coins","description":"Gives you 50 Gold coins"},"screenshotPath":"","applePriceTier":4,"googlePrice":{"data":[150,0,0,0],"num":150.0},"pricingTemplateID":"","descriptions":[]},{"id":"gold100","type":0,"storeIDs":[],"defaultDescription":{"googleLocale":4,"title":"Gives you 100 Gold coins","description":"Gives you 100 Gold coins"},"screenshotPath":"","applePriceTier":5,"googlePrice":{"data":[210,0,0,0],"num":210.0},"pricingTemplateID":"","descriptions":[]},{"id":"gold500","type":0,"storeIDs":[],"defaultDescription":{"googleLocale":4,"title":"Gives you 500 Gold coins","description":"Gives you 500 Gold coins"},"screenshotPath":"","applePriceTier":8,"googlePrice":{"data":[450,0,0,0],"num":450.0},"pricingTemplateID":"","descriptions":[]}]}